blitz_ca/__init__.py
blitz_ca/ca.py
blitz_ca/__main__.py
blitz_ca/cmdline.py
blitz_ca/util.py
blitz_ca/database.py
blitz_ca-0.1.1.dist-info/zip-safe
blitz_ca-0.1.1.dist-info/METADATA
blitz_ca-0.1.1.dist-info/DESCRIPTION.rst
blitz_ca-0.1.1.dist-info/RECORD
blitz_ca-0.1.1.dist-info/metadata.json
blitz_ca-0.1.1.dist-info/WHEEL
blitz_ca-0.1.1.dist-info/top_level.txt
blitz_ca-0.1.1.dist-info/entry_points.txt
