Metadata-Version: 2.0
Name: blitz-ca
Version: 0.1.1
Summary: Certificate authority for humans
Home-page: http://blitz.works/blitz-ca
Author: Da_Blitz
Author-email: code@blitz.works
License: MIT BSD
Download-URL: http://blitz.works/blitz-ca/archive/tip.zip
Keywords: ssl x509 openssl certificate authority
Platform: UNKNOWN
Classifier: Development Status :: 5 - Production/Stable
Classifier: Environment :: Console
Classifier: Intended Audience :: Developers
Classifier: Intended Audience :: System Administrators
Classifier: License :: OSI Approved :: BSD License
Classifier: Operating System :: POSIX :: Linux
Classifier: Programming Language :: Python :: 3
Classifier: Topic :: Communications
Classifier: Topic :: Communications :: Email
Classifier: Topic :: Internet
Classifier: Topic :: Security
Classifier: Topic :: Security :: Cryptography
Classifier: Topic :: System :: Systems Administration
Classifier: Topic :: Utilities
Requires-Dist: pyOpenSSL (>=0.14)
Requires-Dist: SQLAlchemy (>=0.9.7)
Requires-Dist: humanize (>=0.5)
Requires-Dist: pyasn1 (>=0.1.7)
